main_entrypoint/__init__.py
main_entrypoint/entrypoint.py
main_entrypoint-0.1.3.dist-info/LICENSE
main_entrypoint-0.1.3.dist-info/WHEEL
main_entrypoint-0.1.3.dist-info/METADATA
main_entrypoint-0.1.3.dist-info/RECORD
