Metadata-Version: 2.1
Name: main-entrypoint
Version: 0.1.3
Summary: 
Home-page: https://github.com/jstriebel/main-entrypoint
License: MIT
Author: Jonathan Striebel
Requires-Python: >=3.7,<4.0
Classifier: License :: OSI Approved :: MIT License
Classifier: Programming Language :: Python :: 3
Classifier: Programming Language :: Python :: 3.10
Classifier: Programming Language :: Python :: 3.7
Classifier: Programming Language :: Python :: 3.8
Classifier: Programming Language :: Python :: 3.9
Requires-Dist: typing-extensions (>=4.2.0,<5.0.0)
Project-URL: Repository, https://github.com/jstriebel/main-entrypoint
